{"@context":"http://iiif.io/api/image/2/context.json","@id":"https://digital.lib.uiowa.edu/iiif/2/ui:atlases_12463~JP2~~default_public","protocol":"http://iiif.io/api/image","width":3312,"height":4513,"sizes":[{"width":104,"height":141},{"width":207,"height":282},{"width":414,"height":564},{"width":828,"height":1128},{"width":1656,"height":2257},{"width":3312,"height":4513}],"tiles":[{"width":512,"height":512,"scaleFactors":[1,2,4,8,16,32]}],"profile":["http://iiif.io/api/image/2/level2.json",{"formats":["jpg","tif","gif","png"],"maxArea":14947056,"qualities":["bitonal","default","gray","color"],"supports":["regionByPx","sizeByW","sizeByWhListed","cors","regionSquare","sizeByDistortedWh","canonicalLinkHeader","sizeByConfinedWh","sizeByPct","jsonldMediaType","regionByPct","rotationArbitrary","sizeByH","baseUriRedirect","rotationBy90s","profileLinkHeader","sizeByForcedWh","sizeByWh","mirroring"]}]}